tau_tools/__init__.py
tau_tools/collect.py
tau_tools/courses.py
tau_tools/ims.py
tau_tools/logging.py
tau_tools/moodle.py
tau_tools/moodle_exams.py
tau_tools/plans.py
tau_tools/utilities.py
tau_tools-1.1.8.dist-info/METADATA
tau_tools-1.1.8.dist-info/WHEEL
tau_tools-1.1.8.dist-info/licenses/LICENSE.md
tau_tools-1.1.8.dist-info/RECORD
