Metadata-Version: 2.3
Name: tau-tools
Version: 1.1.8
Summary: Tools for accessing and using Tel Aviv University websites
Author-email: Arazim Project <144990276+arazonim@users.noreply.github.com>
License-File: LICENSE.md
Requires-Python: >=3.8
Requires-Dist: beautifulsoup4>=4.12.3
Requires-Dist: requests>=2.32.3
Requires-Dist: rich>=13.7.1
